{"nodes": [{"id": "users_erik_projects_wivuullegiance_client_scripts_lensflare_cs", "label": "LensFlare.cs", "file_type": "code", "source_file": "scripts/LensFlare.cs", "source_location": "L1"}, {"id": "scripts_lensflare_lensflare", "label": "LensFlare", "file_type": "code", "source_file": "scripts/LensFlare.cs", "source_location": "L15"}, {"id": "control", "label": "Control", "file_type": "code", "source_file": "", "source_location": ""}, {"id": "float", "label": "float", "file_type": "code", "source_file": "scripts/LensFlare.cs", "source_location": "L18"}, {"id": "color", "label": "Color", "file_type": "code", "source_file": "scripts/LensFlare.cs", "source_location": "L35"}, {"id": "gradienttexture2d", "label": "GradientTexture2D", "file_type": "code", "source_file": "scripts/LensFlare.cs", "source_location": "L38"}, {"id": "camera3d", "label": "Camera3D", "file_type": "code", "source_file": "scripts/LensFlare.cs", "source_location": "L40"}, {"id": "vector2", "label": "Vector2", "file_type": "code", "source_file": "scripts/LensFlare.cs", "source_location": "L46"}, {"id": "scripts_lensflare_lensflare_init", "label": ".Init()", "file_type": "code", "source_file": "scripts/LensFlare.cs", "source_location": "L50"}, {"id": "scripts_lensflare_lensflare_ready", "label": "._Ready()", "file_type": "code", "source_file": "scripts/LensFlare.cs", "source_location": "L60"}, {"id": "scripts_lensflare_lensflare_process", "label": "._Process()", "file_type": "code", "source_file": "scripts/LensFlare.cs", "source_location": "L73"}, {"id": "scripts_lensflare_lensflare_draw", "label": "._Draw()", "file_type": "code", "source_file": "scripts/LensFlare.cs", "source_location": "L107"}, {"id": "scripts_lensflare_lensflare_tint", "label": ".Tint()", "file_type": "code", "source_file": "scripts/LensFlare.cs", "source_location": "L132"}, {"id": "scripts_lensflare_lensflare_drawsprite", "label": ".DrawSprite()", "file_type": "code", "source_file": "scripts/LensFlare.cs", "source_location": "L135"}, {"id": "texture2d", "label": "Texture2D", "file_type": "code", "source_file": "scripts/LensFlare.cs", "source_location": "L135"}, {"id": "scripts_lensflare_lensflare_drawstretched", "label": ".DrawStretched()", "file_type": "code", "source_file": "scripts/LensFlare.cs", "source_location": "L142"}, {"id": "scripts_lensflare_lensflare_radialtexture", "label": ".RadialTexture()", "file_type": "code", "source_file": "scripts/LensFlare.cs", "source_location": "L150"}, {"id": "gradient", "label": "Gradient", "file_type": "code", "source_file": "scripts/LensFlare.cs", "source_location": "L150"}], "edges": [{"source": "users_erik_projects_wivuullegiance_client_scripts_lensflare_cs", "target": "godot", "relation": "imports", "context": "import", "confidence": "EXTRACTED", "source_file": "scripts/LensFlare.cs", "source_location": "L1", "weight": 1.0}, {"source": "users_erik_projects_wivuullegiance_client_scripts_lensflare_cs", "target": "scripts_lensflare_lensflare", "relation": "contains", "confidence": "EXTRACTED", "source_file": "scripts/LensFlare.cs", "source_location": "L15", "weight": 1.0}, {"source": "scripts_lensflare_lensflare", "target": "control", "relation": "inherits", "confidence": "EXTRACTED", "source_file": "scripts/LensFlare.cs", "source_location": "L15", "weight": 1.0}, {"source": "scripts_lensflare_lensflare", "target": "float", "relation": "references", "confidence": "EXTRACTED", "source_file": "scripts/LensFlare.cs", "source_location": "L18", "weight": 1.0, "context": "field"}, {"source": "scripts_lensflare_lensflare", "target": "float", "relation": "references", "confidence": "EXTRACTED", "source_file": "scripts/LensFlare.cs", "source_location": "L21", "weight": 1.0, "context": "field"}, {"source": "scripts_lensflare_lensflare", "target": "float", "relation": "references", "confidence": "EXTRACTED", "source_file": "scripts/LensFlare.cs", "source_location": "L22", "weight": 1.0, "context": "field"}, {"source": "scripts_lensflare_lensflare", "target": "float", "relation": "references", "confidence": "EXTRACTED", "source_file": "scripts/LensFlare.cs", "source_location": "L26", "weight": 1.0, "context": "field"}, {"source": "scripts_lensflare_lensflare", "target": "float", "relation": "references", "confidence": "EXTRACTED", "source_file": "scripts/LensFlare.cs", "source_location": "L27", "weight": 1.0, "context": "field"}, {"source": "scripts_lensflare_lensflare", "target": "float", "relation": "references", "confidence": "EXTRACTED", "source_file": "scripts/LensFlare.cs", "source_location": "L28", "weight": 1.0, "context": "field"}, {"source": "scripts_lensflare_lensflare", "target": "float", "relation": "references", "confidence": "EXTRACTED", "source_file": "scripts/LensFlare.cs", "source_location": "L30", "weight": 1.0, "context": "field"}, {"source": "scripts_lensflare_lensflare", "target": "float", "relation": "references", "confidence": "EXTRACTED", "source_file": "scripts/LensFlare.cs", "source_location": "L31", "weight": 1.0, "context": "field"}, {"source": "scripts_lensflare_lensflare", "target": "float", "relation": "references", "confidence": "EXTRACTED", "source_file": "scripts/LensFlare.cs", "source_location": "L32", "weight": 1.0, "context": "field"}, {"source": "scripts_lensflare_lensflare", "target": "color", "relation": "references", "confidence": "EXTRACTED", "source_file": "scripts/LensFlare.cs", "source_location": "L35", "weight": 1.0, "context": "field"}, {"source": "scripts_lensflare_lensflare", "target": "color", "relation": "references", "confidence": "EXTRACTED", "source_file": "scripts/LensFlare.cs", "source_location": "L36", "weight": 1.0, "context": "field"}, {"source": "scripts_lensflare_lensflare", "target": "gradienttexture2d", "relation": "references", "confidence": "EXTRACTED", "source_file": "scripts/LensFlare.cs", "source_location": "L38", "weight": 1.0, "context": "field"}, {"source": "scripts_lensflare_lensflare", "target": "camera3d", "relation": "references", "confidence": "EXTRACTED", "source_file": "scripts/LensFlare.cs", "source_location": "L40", "weight": 1.0, "context": "field"}, {"source": "scripts_lensflare_lensflare", "target": "vector2", "relation": "references", "confidence": "EXTRACTED", "source_file": "scripts/LensFlare.cs", "source_location": "L46", "weight": 1.0, "context": "field"}, {"source": "scripts_lensflare_lensflare", "target": "float", "relation": "references", "confidence": "EXTRACTED", "source_file": "scripts/LensFlare.cs", "source_location": "L47", "weight": 1.0, "context": "field"}, {"source": "scripts_lensflare_lensflare", "target": "scripts_lensflare_lensflare_init", "relation": "method", "confidence": "EXTRACTED", "source_file": "scripts/LensFlare.cs", "source_location": "L50", "weight": 1.0}, {"source": "scripts_lensflare_lensflare_init", "target": "camera3d", "relation": "references", "confidence": "EXTRACTED", "source_file": "scripts/LensFlare.cs", "source_location": "L50", "weight": 1.0, "context": "parameter_type"}, {"source": "scripts_lensflare_lensflare", "target": "scripts_lensflare_lensflare_ready", "relation": "method", "confidence": "EXTRACTED", "source_file": "scripts/LensFlare.cs", "source_location": "L60", "weight": 1.0}, {"source": "scripts_lensflare_lensflare", "target": "scripts_lensflare_lensflare_process", "relation": "method", "confidence": "EXTRACTED", "source_file": "scripts/LensFlare.cs", "source_location": "L73", "weight": 1.0}, {"source": "scripts_lensflare_lensflare", "target": "scripts_lensflare_lensflare_draw", "relation": "method", "confidence": "EXTRACTED", "source_file": "scripts/LensFlare.cs", "source_location": "L107", "weight": 1.0}, {"source": "scripts_lensflare_lensflare", "target": "scripts_lensflare_lensflare_tint", "relation": "method", "confidence": "EXTRACTED", "source_file": "scripts/LensFlare.cs", "source_location": "L132", "weight": 1.0}, {"source": "scripts_lensflare_lensflare_tint", "target": "color", "relation": "references", "confidence": "EXTRACTED", "source_file": "scripts/LensFlare.cs", "source_location": "L132", "weight": 1.0, "context": "parameter_type"}, {"source": "scripts_lensflare_lensflare_tint", "target": "color", "relation": "references", "confidence": "EXTRACTED", "source_file": "scripts/LensFlare.cs", "source_location": "L132", "weight": 1.0, "context": "return_type"}, {"source": "scripts_lensflare_lensflare", "target": "scripts_lensflare_lensflare_drawsprite", "relation": "method", "confidence": "EXTRACTED", "source_file": "scripts/LensFlare.cs", "source_location": "L135", "weight": 1.0}, {"source": "scripts_lensflare_lensflare_drawsprite", "target": "texture2d", "relation": "references", "confidence": "EXTRACTED", "source_file": "scripts/LensFlare.cs", "source_location": "L135", "weight": 1.0, "context": "parameter_type"}, {"source": "scripts_lensflare_lensflare_drawsprite", "target": "vector2", "relation": "references", "confidence": "EXTRACTED", "source_file": "scripts/LensFlare.cs", "source_location": "L135", "weight": 1.0, "context": "parameter_type"}, {"source": "scripts_lensflare_lensflare_drawsprite", "target": "color", "relation": "references", "confidence": "EXTRACTED", "source_file": "scripts/LensFlare.cs", "source_location": "L135", "weight": 1.0, "context": "parameter_type"}, {"source": "scripts_lensflare_lensflare", "target": "scripts_lensflare_lensflare_drawstretched", "relation": "method", "confidence": "EXTRACTED", "source_file": "scripts/LensFlare.cs", "source_location": "L142", "weight": 1.0}, {"source": "scripts_lensflare_lensflare_drawstretched", "target": "texture2d", "relation": "references", "confidence": "EXTRACTED", "source_file": "scripts/LensFlare.cs", "source_location": "L142", "weight": 1.0, "context": "parameter_type"}, {"source": "scripts_lensflare_lensflare_drawstretched", "target": "vector2", "relation": "references", "confidence": "EXTRACTED", "source_file": "scripts/LensFlare.cs", "source_location": "L142", "weight": 1.0, "context": "parameter_type"}, {"source": "scripts_lensflare_lensflare_drawstretched", "target": "color", "relation": "references", "confidence": "EXTRACTED", "source_file": "scripts/LensFlare.cs", "source_location": "L142", "weight": 1.0, "context": "parameter_type"}, {"source": "scripts_lensflare_lensflare", "target": "scripts_lensflare_lensflare_radialtexture", "relation": "method", "confidence": "EXTRACTED", "source_file": "scripts/LensFlare.cs", "source_location": "L150", "weight": 1.0}, {"source": "scripts_lensflare_lensflare_radialtexture", "target": "gradient", "relation": "references", "confidence": "EXTRACTED", "source_file": "scripts/LensFlare.cs", "source_location": "L150", "weight": 1.0, "context": "parameter_type"}, {"source": "scripts_lensflare_lensflare_radialtexture", "target": "gradienttexture2d", "relation": "references", "confidence": "EXTRACTED", "source_file": "scripts/LensFlare.cs", "source_location": "L150", "weight": 1.0, "context": "return_type"}, {"source": "scripts_lensflare_lensflare_ready", "target": "scripts_lensflare_lensflare_radialtexture", "relation": "calls", "context": "call", "confidence": "EXTRACTED", "source_file": "scripts/LensFlare.cs", "source_location": "L64", "weight": 1.0}, {"source": "scripts_lensflare_lensflare_draw", "target": "scripts_lensflare_lensflare_drawsprite", "relation": "calls", "context": "call", "confidence": "EXTRACTED", "source_file": "scripts/LensFlare.cs", "source_location": "L116", "weight": 1.0}, {"source": "scripts_lensflare_lensflare_draw", "target": "scripts_lensflare_lensflare_tint", "relation": "calls", "context": "call", "confidence": "EXTRACTED", "source_file": "scripts/LensFlare.cs", "source_location": "L116", "weight": 1.0}, {"source": "scripts_lensflare_lensflare_draw", "target": "scripts_lensflare_lensflare_drawstretched", "relation": "calls", "context": "call", "confidence": "EXTRACTED", "source_file": "scripts/LensFlare.cs", "source_location": "L127", "weight": 1.0}], "raw_calls": [{"caller_nid": "scripts_lensflare_lensflare_init", "callee": "SetAnchorsPreset", "is_member_call": false, "source_file": "/Users/erik/projects/wivuullegiance/client/scripts/LensFlare.cs", "source_location": "L53"}, {"caller_nid": "scripts_lensflare_lensflare_process", "callee": "IsPositionBehind", "is_member_call": true, "source_file": "/Users/erik/projects/wivuullegiance/client/scripts/LensFlare.cs", "source_location": "L86"}, {"caller_nid": "scripts_lensflare_lensflare_process", "callee": "QueueRedraw", "is_member_call": false, "source_file": "/Users/erik/projects/wivuullegiance/client/scripts/LensFlare.cs", "source_location": "L88"}, {"caller_nid": "scripts_lensflare_lensflare_process", "callee": "UnprojectPosition", "is_member_call": true, "source_file": "/Users/erik/projects/wivuullegiance/client/scripts/LensFlare.cs", "source_location": "L92"}, {"caller_nid": "scripts_lensflare_lensflare_process", "callee": "GetViewportRect", "is_member_call": false, "source_file": "/Users/erik/projects/wivuullegiance/client/scripts/LensFlare.cs", "source_location": "L97"}, {"caller_nid": "scripts_lensflare_lensflare_process", "callee": "Length", "is_member_call": true, "source_file": "/Users/erik/projects/wivuullegiance/client/scripts/LensFlare.cs", "source_location": "L99"}, {"caller_nid": "scripts_lensflare_lensflare_process", "callee": "Length", "is_member_call": true, "source_file": "/Users/erik/projects/wivuullegiance/client/scripts/LensFlare.cs", "source_location": "L100"}, {"caller_nid": "scripts_lensflare_lensflare_process", "callee": "SmoothStep", "is_member_call": true, "source_file": "/Users/erik/projects/wivuullegiance/client/scripts/LensFlare.cs", "source_location": "L101"}, {"caller_nid": "scripts_lensflare_lensflare_process", "callee": "QueueRedraw", "is_member_call": false, "source_file": "/Users/erik/projects/wivuullegiance/client/scripts/LensFlare.cs", "source_location": "L104"}, {"caller_nid": "scripts_lensflare_lensflare_draw", "callee": "GetViewportRect", "is_member_call": false, "source_file": "/Users/erik/projects/wivuullegiance/client/scripts/LensFlare.cs", "source_location": "L112"}, {"caller_nid": "scripts_lensflare_lensflare_drawsprite", "callee": "DrawTextureRect", "is_member_call": false, "source_file": "/Users/erik/projects/wivuullegiance/client/scripts/LensFlare.cs", "source_location": "L138"}, {"caller_nid": "scripts_lensflare_lensflare_drawstretched", "callee": "DrawTextureRect", "is_member_call": false, "source_file": "/Users/erik/projects/wivuullegiance/client/scripts/LensFlare.cs", "source_location": "L145"}]}